pycparserext_gnuc/__init__.py
pycparserext_gnuc/_build_tables.py
pycparserext_gnuc/c_generator.py
pycparserext_gnuc/ext_c_generator.py
pycparserext_gnuc/ext_c_lexer.py
pycparserext_gnuc/ext_c_parser.py
pycparserext_gnuc/lextab.py
pycparserext_gnuc/yacctab.py
pycparserext_gnuc-2022.10.dist-info/LICENSE
pycparserext_gnuc-2022.10.dist-info/METADATA
pycparserext_gnuc-2022.10.dist-info/WHEEL
pycparserext_gnuc-2022.10.dist-info/top_level.txt
pycparserext_gnuc-2022.10.dist-info/RECORD
