Metadata-Version: 2.1
Name: pycparserext-gnuc
Version: 2022.10
Summary: GNU C extension for pycparser, based on inducer/pycparseext
Home-page: http://pypi.python.org/pypi/pycparserext
Author: Andreas Kloeckner
Author-email: inform@tiker.net
License: MIT
Platform: UNKNOWN
Classifier: Development Status :: 4 - Beta
Classifier: Intended Audience :: Developers
Classifier: Intended Audience :: Other Audience
Classifier: Intended Audience :: Science/Research
Classifier: License :: OSI Approved :: MIT License
Classifier: Natural Language :: English
Classifier: Programming Language :: Python
Classifier: Topic :: Utilities
Requires-Python: >=3.6
Requires-Dist: ply (>=3.4)
Requires-Dist: pycparser (>=2.18)
